incolor/__init__.py
incolor-0.2.dist-info/LICENSE
incolor-0.2.dist-info/METADATA
incolor-0.2.dist-info/WHEEL
incolor-0.2.dist-info/top_level.txt
incolor-0.2.dist-info/RECORD
