Metadata-Version: 2.1
Name: incolor
Version: 0.2
Summary: Add color codes to strings or print in color.
Home-page: https://github.com/filwie/incolor
Author: Filip Wiechec
Author-email: filip.wiechec@gmail.com
License: MIT
Keywords: color
Platform: UNKNOWN
Classifier: Programming Language :: Python :: 3
Classifier: License :: OSI Approved :: MIT License
Requires-Python: >=3.6
